<?xml version="1.0" encoding="UTF-8" standalone="no"?>
<sqlMap namespace="NYEL8899Query">

    <statement id="getProcInstExtAttr" parameterClass="Map" resultMap="resultCMsg">
        SELECT
          WF_PROC_NM
          , WF_PROC_DOC_ID
          , WF_TEST_PTRN_NM AS WF_DATA_NM
          , WF_CLS_NM
          , WF_DATA_NM AS WF_TEST_PTRN_NM
          , WF_BIZ_ATTRB_TXT_01
          , WF_BIZ_ATTRB_TXT_02
          , WF_BIZ_ATTRB_TXT_03
          , WF_BIZ_ATTRB_TXT_04
          , WF_BIZ_ATTRB_TXT_05
          , WF_BIZ_ATTRB_TXT_06
          , WF_BIZ_ATTRB_TXT_07
          , WF_BIZ_ATTRB_TXT_08
          , WF_BIZ_ATTRB_TXT_09
          , WF_BIZ_ATTRB_TXT_10
          , WF_BIZ_ATTRB_LB_TXT_01
          , WF_BIZ_ATTRB_LB_TXT_02
          , WF_BIZ_ATTRB_LB_TXT_03
          , WF_BIZ_ATTRB_LB_TXT_04
          , WF_BIZ_ATTRB_LB_TXT_05
          , WF_BIZ_ATTRB_LB_TXT_06
          , WF_BIZ_ATTRB_LB_TXT_07
          , WF_BIZ_ATTRB_LB_TXT_08
          , WF_BIZ_ATTRB_LB_TXT_09
          , WF_BIZ_ATTRB_LB_TXT_10
          , COND_VAL_TXT_01
          , COND_VAL_TXT_02
          , COND_VAL_TXT_03
          , COND_VAL_TXT_04
          , COND_VAL_TXT_05
          , COND_VAL_TXT_06
          , COND_VAL_TXT_07
          , COND_VAL_TXT_08
          , COND_VAL_TXT_09
          , COND_VAL_TXT_10
          , COND_VAL_NUM_01
          , COND_VAL_NUM_02
          , COND_VAL_NUM_03
          , COND_VAL_NUM_04
          , COND_VAL_NUM_05
          , COND_VAL_NUM_06
          , COND_VAL_NUM_07
          , COND_VAL_NUM_08
          , COND_VAL_NUM_09
          , COND_VAL_NUM_10
        FROM
          WF_SUBMT_INFO 
        WHERE
          WF_PROC_NM = #wfProcNm#
          AND WF_TEST_PTRN_NM = #wfDataNm#  
          AND GLBL_CMPY_CD = #glblCmpyCd# 
          AND EZCANCELFLAG       = '0'
    </statement>

    <typeAlias alias="NYEL8899CMsg"    type="business.blap.NYEL8899.NYEL8899CMsg"/>

    <resultMap id="resultCMsg" class="NYEL8899CMsg">
        <result property="wfProcNm"	column="WF_PROC_NM"	javaType="EZDSStringItem"/>
        <result property="wfTestPtrnNm"	column="WF_TEST_PTRN_NM"	javaType="EZDSStringItem"/>
        <result property="wfClsNm"	column="WF_CLS_NM"	javaType="EZDSStringItem"/>
        <result property="wfDataNm"	column="WF_DATA_NM"	javaType="EZDSStringItem"/>
        <result property="wfProcDocId"	column="WF_PROC_DOC_ID"	javaType="EZDSStringItem"/>
        <result property="wfBizAttrbTxt_01"	column="WF_BIZ_ATTRB_TXT_01"	javaType="EZDSStringItem"/>
        <result property="wfBizAttrbTxt_02"	column="WF_BIZ_ATTRB_TXT_02"	javaType="EZDSStringItem"/>
        <result property="wfBizAttrbTxt_03"	column="WF_BIZ_ATTRB_TXT_03"	javaType="EZDSStringItem"/>
        <result property="wfBizAttrbTxt_04"	column="WF_BIZ_ATTRB_TXT_04"	javaType="EZDSStringItem"/>
        <result property="wfBizAttrbTxt_05"	column="WF_BIZ_ATTRB_TXT_05"	javaType="EZDSStringItem"/>
        <result property="wfBizAttrbTxt_06"	column="WF_BIZ_ATTRB_TXT_06"	javaType="EZDSStringItem"/>
        <result property="wfBizAttrbTxt_07"	column="WF_BIZ_ATTRB_TXT_07"	javaType="EZDSStringItem"/>
        <result property="wfBizAttrbTxt_08"	column="WF_BIZ_ATTRB_TXT_08"	javaType="EZDSStringItem"/>
        <result property="wfBizAttrbTxt_09"	column="WF_BIZ_ATTRB_TXT_09"	javaType="EZDSStringItem"/>
        <result property="wfBizAttrbTxt_10"	column="WF_BIZ_ATTRB_TXT_10"	javaType="EZDSStringItem"/>
        <result property="wfBizAttrbLbTxt_01"	column="WF_BIZ_ATTRB_LB_TXT_01"	javaType="EZDSStringItem"/>
        <result property="wfBizAttrbLbTxt_02"	column="WF_BIZ_ATTRB_LB_TXT_02"	javaType="EZDSStringItem"/>
        <result property="wfBizAttrbLbTxt_03"	column="WF_BIZ_ATTRB_LB_TXT_03"	javaType="EZDSStringItem"/>
        <result property="wfBizAttrbLbTxt_04"	column="WF_BIZ_ATTRB_LB_TXT_04"	javaType="EZDSStringItem"/>
        <result property="wfBizAttrbLbTxt_05"	column="WF_BIZ_ATTRB_LB_TXT_05"	javaType="EZDSStringItem"/>
        <result property="wfBizAttrbLbTxt_06"	column="WF_BIZ_ATTRB_LB_TXT_06"	javaType="EZDSStringItem"/>
        <result property="wfBizAttrbLbTxt_07"	column="WF_BIZ_ATTRB_LB_TXT_07"	javaType="EZDSStringItem"/>
        <result property="wfBizAttrbLbTxt_08"	column="WF_BIZ_ATTRB_LB_TXT_08"	javaType="EZDSStringItem"/>
        <result property="wfBizAttrbLbTxt_09"	column="WF_BIZ_ATTRB_LB_TXT_09"	javaType="EZDSStringItem"/>
        <result property="wfBizAttrbLbTxt_10"	column="WF_BIZ_ATTRB_LB_TXT_10"	javaType="EZDSStringItem"/>
        <result property="condValTxt_01"	column="COND_VAL_TXT_01"	javaType="EZDSStringItem"/>
        <result property="condValTxt_02"	column="COND_VAL_TXT_02"	javaType="EZDSStringItem"/>
        <result property="condValTxt_03"	column="COND_VAL_TXT_03"	javaType="EZDSStringItem"/>
        <result property="condValTxt_04"	column="COND_VAL_TXT_04"	javaType="EZDSStringItem"/>
        <result property="condValTxt_05"	column="COND_VAL_TXT_05"	javaType="EZDSStringItem"/>
        <result property="condValTxt_06"	column="COND_VAL_TXT_06"	javaType="EZDSStringItem"/>
        <result property="condValTxt_07"	column="COND_VAL_TXT_07"	javaType="EZDSStringItem"/>
        <result property="condValTxt_08"	column="COND_VAL_TXT_08"	javaType="EZDSStringItem"/>
        <result property="condValTxt_09"	column="COND_VAL_TXT_09"	javaType="EZDSStringItem"/>
        <result property="condValTxt_10"	column="COND_VAL_TXT_10"	javaType="EZDSStringItem"/>
        <result property="condValNum_01"	column="COND_VAL_NUM_01"	javaType="EZDSBigDecimalItem"/>
        <result property="condValNum_02"	column="COND_VAL_NUM_02"	javaType="EZDSBigDecimalItem"/>
        <result property="condValNum_03"	column="COND_VAL_NUM_03"	javaType="EZDSBigDecimalItem"/>
        <result property="condValNum_04"	column="COND_VAL_NUM_04"	javaType="EZDSBigDecimalItem"/>
        <result property="condValNum_05"	column="COND_VAL_NUM_05"	javaType="EZDSBigDecimalItem"/>
        <result property="condValNum_06"	column="COND_VAL_NUM_06"	javaType="EZDSBigDecimalItem"/>
        <result property="condValNum_07"	column="COND_VAL_NUM_07"	javaType="EZDSBigDecimalItem"/>
        <result property="condValNum_08"	column="COND_VAL_NUM_08"	javaType="EZDSBigDecimalItem"/>
        <result property="condValNum_09"	column="COND_VAL_NUM_09"	javaType="EZDSBigDecimalItem"/>
        <result property="condValNum_10"	column="COND_VAL_NUM_10"	javaType="EZDSBigDecimalItem"/>
    </resultMap>

</sqlMap>
